{
  "version": "1.0",
  "callsign": "W8MB",
  "state": "off_air",
  "activity": "Listening",
  "frequency": {
    "value": "Local",
    "unit": "MHz",
    "band": "2m"
  },
  "mode": "DMR",
  "location": {
    "description": "Mansfield, MO",
    "grid_square": "EM37",
    "reference": "Local Repeater"
  },
  "custom_message": "Monitoring the local repeater. Drop a call!",
  "last_updated": "2026-07-19T18:36:52Z",
  "aprs": {
    "last_beacon": "2026-07-19T18:38:19Z",
    "position": {
      "lat": 37.11,
      "lon": -92.58
    },
    "symbol": "/a",
    "course": 322,
    "speed_mph": 0,
    "altitude_ft": null,
    "comment": "William",
    "last_message": {
      "to": "W8MB",
      "text": "Test message{2",
      "time": "2026-07-19T02:55:17Z"
    }
  },
  "last_heard": {
    "mode": "DMR",
    "talkgroup": 31291,
    "talkgroup_name": "SWMO",
    "network": "BrandMeister",
    "time": "2026-07-19T18:36:52Z"
  }
}